nonebot_plugin_smallapi/__init__.py
nonebot_plugin_smallapi/api_menu.py
nonebot_plugin_smallapi/api_pic.py
nonebot_plugin_smallapi/api_site.py
nonebot_plugin_smallapi/api_text.py
nonebot_plugin_smallapi/config.py
nonebot_plugin_smallapi/hander.py
nonebot_plugin_smallapi/hander_site.py
nonebot_plugin_smallapi-1.1.7.dist-info/LICENSE
nonebot_plugin_smallapi-1.1.7.dist-info/METADATA
nonebot_plugin_smallapi-1.1.7.dist-info/WHEEL
nonebot_plugin_smallapi-1.1.7.dist-info/top_level.txt
nonebot_plugin_smallapi-1.1.7.dist-info/RECORD
