Metadata-Version: 2.2
Name: nonebot_plugin_smallapi
Version: 1.1.7
Summary: A small nonebot_plugin_smallapi plugin
Home-page: https://github.com/chaichaisi/nonebot_plugin_smallapi
Author: Chaichaisi
Author-email: chaichaisi@qq.com
Classifier: Programming Language :: Python :: 3
Classifier: License :: OSI Approved :: MIT License
Classifier: Operating System :: OS Independent
Requires-Python: >=3.10
License-File: LICENSE
Requires-Dist: jsonpath
Requires-Dist: nonebot2[aiohttp]
Requires-Dist: nonebot-adapter-onebot
Requires-Dist: nonebot2[httpx]
Dynamic: author
Dynamic: author-email
Dynamic: classifier
Dynamic: description
Dynamic: description-content-type
Dynamic: home-page
Dynamic: requires-dist
Dynamic: requires-python
Dynamic: summary
